LICENSE
MANIFEST.in
README.rst
setup.py
serious_django_enums/__init__.py
serious_django_enums.egg-info/PKG-INFO
serious_django_enums.egg-info/SOURCES.txt
serious_django_enums.egg-info/dependency_links.txt
serious_django_enums.egg-info/requires.txt
serious_django_enums.egg-info/top_level.txt